hpfc/__init__.py
hpfc/cli.py
hpfc/core.py
hpfc_tool-0.2.0.dist-info/licenses/LICENSE
hpfc_tool-0.2.0.dist-info/METADATA
hpfc_tool-0.2.0.dist-info/WHEEL
hpfc_tool-0.2.0.dist-info/entry_points.txt
hpfc_tool-0.2.0.dist-info/top_level.txt
hpfc_tool-0.2.0.dist-info/RECORD
