Metadata-Version: 2.4
Name: hpfc-tool
Version: 0.2.0
Summary: A high-performance directory comparison tool
Home-page: https://github.com/ethan-li/hpfc
Author: Ethan Li
Keywords: directory,folder,comparison,diff,file comparison
Classifier: Development Status :: 4 - Beta
Classifier: Intended Audience :: Developers
Classifier: Intended Audience :: System Administrators
Classifier: License :: OSI Approved :: MIT License
Classifier: Programming Language :: Python :: 3.11
Classifier: Operating System :: OS Independent
Classifier: Topic :: System :: Filesystems
Classifier: Topic :: Utilities
Requires-Python: >=3.11,<4
License-File: LICENSE
Requires-Dist: jinja2>=2.11.0
Provides-Extra: dev
Requires-Dist: pytest>=6.0.0; extra == "dev"
Requires-Dist: pytest-cov>=2.10.0; extra == "dev"
Requires-Dist: black>=20.8b1; extra == "dev"
Requires-Dist: isort>=5.0.0; extra == "dev"
Requires-Dist: mypy>=0.800; extra == "dev"
Requires-Dist: flake8>=3.8.0; extra == "dev"
Requires-Dist: build>=0.7.0; extra == "dev"
Requires-Dist: twine>=3.4.0; extra == "dev"
Dynamic: author
Dynamic: classifier
Dynamic: description
Dynamic: description-content-type
Dynamic: home-page
Dynamic: keywords
Dynamic: license-file
Dynamic: provides-extra
Dynamic: requires-dist
Dynamic: requires-python
Dynamic: summary
